[{"id":1,"name":"Boyareddypalli","state":"Andhra Pradesh","lat":14.88,"lng":77.92,"capacity_tpa":0,"production_cost":0,"safety_stock":0,"city":"Boyareddypalli","source_url":"https://www.adani.com/businesses/materials/cement","plant_type":"Integrated Unit","company_brand":"Penna"},{"id":2,"name":"Talaricheruvu","state":"Andhra Pradesh","lat":14.92,"lng":78.02,"capacity_tpa":0,"production_cost":0,"safety_stock":0,"city":"Talaricheruvu","source_url":"https://www.adani.com/businesses/materials/cement","plant_type":"Integrated Unit","company_brand":"Penna"},{"id":3,"name":"Jamul","state":"Chhattisgarh","lat":21.19,"lng":81.4,"capacity_tpa":0,"production_cost":0,"safety_stock":0,"city":"Jamul","source_url":"https://www.adani.com/businesses/materials/cement","plant_type":"Integrated Unit","company_brand":"ACC"},{"id":4,"name":"Bhatapara","state":"Chhattisgarh","lat":21.73,"lng":81.93,"capacity_tpa":0,"production_cost":0,"safety_stock":0,"city":"Bhatapara","source_url":"https://www.adani.com/businesses/materials/cement","plant_type":"Integrated Unit","company_brand":"Ambuja"},{"id":5,"name":"Sanghi, Kutch","state":"Gujarat","lat":23.2504,"lng":69.6669,"capacity_tpa":0,"production_cost":0,"safety_stock":0,"city":"Kutch","source_url":"https://www.adani.com/businesses/materials/cement","plant_type":"Integrated Unit","company_brand":"Sanghi"},{"id":6,"name":"Ambujanagar","state":"Gujarat","lat":20.95,"lng":70.75,"capacity_tpa":0,"production_cost":0,"safety_stock":0,"city":"Ambujanagar","source_url":"https://www.adani.com/businesses/materials/cement","plant_type":"Integrated Unit","company_brand":"Ambuja"},{"id":7,"name":"Gagal","state":"Himachal Pradesh","lat":31.25,"lng":76.85,"capacity_tpa":0,"production_cost":0,"safety_stock":0,"city":"Gagal","source_url":"https://www.adani.com/businesses/materials/cement","plant_type":"Integrated Unit","company_brand":"ACC"},{"id":8,"name":"Darlaghat (Suli)","state":"Himachal Pradesh","lat":31.24,"lng":76.95,"capacity_tpa":0,"production_cost":0,"safety_stock":0,"city":"Darlaghat","source_url":"https://www.adani.com/businesses/materials/cement","plant_type":"Integrated Unit","company_brand":"Ambuja"},{"id":9,"name":"Chaibasa","state":"Jharkhand","lat":22.55,"lng":85.81,"capacity_tpa":0,"production_cost":0,"safety_stock":0,"city":"Chaibasa","source_url":"https://www.adani.com/businesses/materials/cement","plant_type":"Integrated Unit","company_brand":"ACC"},{"id":10,"name":"Kalaburagi","state":"Karnataka","lat":17.3297,"lng":76.8343,"capacity_tpa":0,"production_cost":0,"safety_stock":0,"city":"Kalaburagi","source_url":"https://www.adani.com/businesses/materials/cement","plant_type":"Integrated Unit","company_brand":"Orient"},{"id":11,"name":"Wadi 1 & 2","state":"Karnataka","lat":17.06,"lng":76.98,"capacity_tpa":0,"production_cost":0,"safety_stock":0,"city":"Wadi","source_url":"https://www.adani.com/businesses/materials/cement","plant_type":"Integrated Unit","company_brand":"ACC"},{"id":12,"name":"Kymore","state":"Madhya Pradesh","lat":24.03,"lng":80.58,"capacity_tpa":0,"production_cost":0,"safety_stock":0,"city":"Kymore","source_url":"https://www.adani.com/businesses/materials/cement","plant_type":"Integrated Unit","company_brand":"ACC"},{"id":13,"name":"Ametha","state":"Madhya Pradesh","lat":23.95,"lng":80.6,"capacity_tpa":0,"production_cost":0,"safety_stock":0,"city":"Ametha","source_url":"https://www.adani.com/businesses/materials/cement","plant_type":"Integrated Unit","company_brand":"ACC"},{"id":14,"name":"Jalgaon","state":"Maharashtra","lat":21.0077,"lng":75.5626,"capacity_tpa":0,"production_cost":0,"safety_stock":0,"city":"Jalgaon","source_url":"https://www.adani.com/businesses/materials/cement","plant_type":"Integrated Unit","company_brand":"Orient"},{"id":15,"name":"Chanda","state":"Maharashtra","lat":19.92,"lng":79.28,"capacity_tpa":0,"production_cost":0,"safety_stock":0,"city":"Chanda","source_url":"https://www.adani.com/businesses/materials/cement","plant_type":"Integrated Unit","company_brand":"ACC"},{"id":16,"name":"Maratha, Solapur","state":"Maharashtra","lat":17.6599,"lng":75.9064,"capacity_tpa":0,"production_cost":0,"safety_stock":0,"city":"Solapur","source_url":"https://www.adani.com/businesses/materials/cement","plant_type":"Integrated Unit","company_brand":"Ambuja"},{"id":17,"name":"Patas","state":"Maharashtra","lat":18.4419,"lng":74.4508,"capacity_tpa":0,"production_cost":0,"safety_stock":0,"city":"Patas","source_url":"https://www.adani.com/businesses/materials/cement","plant_type":"Integrated Unit","company_brand":"Penna"},{"id":18,"name":"Baragrh","state":"Odisha","lat":21.3323,"lng":83.6214,"capacity_tpa":0,"production_cost":0,"safety_stock":0,"city":"Bargarh","source_url":"https://www.adani.com/businesses/materials/cement","plant_type":"Integrated Unit","company_brand":"ACC"},{"id":19,"name":"Marwar Mundwa","state":"Rajasthan","lat":26.91,"lng":73.85,"capacity_tpa":0,"production_cost":0,"safety_stock":0,"city":"Marwar Mundwa","source_url":"https://www.adani.com/businesses/materials/cement","plant_type":"Integrated Unit","company_brand":"Ambuja"},{"id":20,"name":"Rabriyawas","state":"Rajasthan","lat":26.5,"lng":74,"capacity_tpa":0,"production_cost":0,"safety_stock":0,"city":"Rabriyawas","source_url":"https://www.adani.com/businesses/materials/cement","plant_type":"Integrated Unit","company_brand":"Ambuja"},{"id":21,"name":"Jodhpur","state":"Rajasthan","lat":26.2389,"lng":73.0243,"capacity_tpa":0,"production_cost":0,"safety_stock":0,"city":"Jodhpur","source_url":"https://www.adani.com/businesses/materials/cement","plant_type":"Integrated Unit","company_brand":"Penna"},{"id":22,"name":"Lakheri","state":"Rajasthan","lat":25.6667,"lng":76.1667,"capacity_tpa":0,"production_cost":0,"safety_stock":0,"city":"Lakheri","source_url":"https://www.adani.com/businesses/materials/cement","plant_type":"Integrated Unit","company_brand":"ACC"},{"id":23,"name":"Devapur","state":"Telangana","lat":19.03,"lng":79.17,"capacity_tpa":0,"production_cost":0,"safety_stock":0,"city":"Devapur","source_url":"https://www.adani.com/businesses/materials/cement","plant_type":"Integrated Unit","company_brand":"Orient"},{"id":24,"name":"Ganeshpahad","state":"Telangana","lat":16.85,"lng":79.52,"capacity_tpa":0,"production_cost":0,"safety_stock":0,"city":"Ganeshpahad","source_url":"https://www.adani.com/businesses/materials/cement","plant_type":"Integrated Unit","company_brand":"Penna"},{"id":25,"name":"Mancherial","state":"Telangana","lat":18.87,"lng":79.44,"capacity_tpa":0,"production_cost":0,"safety_stock":0,"city":"Mancherial","source_url":"https://www.adani.com/businesses/materials/cement","plant_type":"Integrated Unit","company_brand":"Penna"},{"id":26,"name":"Tandur","state":"Telangana","lat":17.26,"lng":77.59,"capacity_tpa":0,"production_cost":0,"safety_stock":0,"city":"Tandur","source_url":"https://www.adani.com/businesses/materials/cement","plant_type":"Integrated Unit","company_brand":"Penna"}]